pdesolvers/__init__.py
pdesolvers/main.py
pdesolvers/enums/__init__.py
pdesolvers/enums/enums.py
pdesolvers/optionspricing/__init__.py
pdesolvers/optionspricing/black_scholes_formula.py
pdesolvers/optionspricing/market_data.py
pdesolvers/optionspricing/monte_carlo.py
pdesolvers/pdes/__init__.py
pdesolvers/pdes/black_scholes.py
pdesolvers/pdes/heat_1d.py
pdesolvers/solution/__init__.py
pdesolvers/solution/solution.py
pdesolvers/solvers/__init__.py
pdesolvers/solvers/black_scholes_solvers.py
pdesolvers/solvers/heat_solvers.py
pdesolvers/solvers/solver.py
pdesolvers/tests/__init__.py
pdesolvers/tests/test_black_scholes.py
pdesolvers/tests/test_heat_solvers.py
pdesolvers/tests/test_options_pricing.py
pdesolvers/utils/__init__.py
pdesolvers/utils/utility.py
pdesolvers-0.1.2.dist-info/LICENSE.md
pdesolvers-0.1.2.dist-info/METADATA
pdesolvers-0.1.2.dist-info/WHEEL
pdesolvers-0.1.2.dist-info/top_level.txt
pdesolvers-0.1.2.dist-info/RECORD
