Metadata-Version: 2.2
Name: pdesolvers
Version: 0.1.2
Summary: A package for solving partial differential equations
Home-page: https://github.com/GPUEngineering/PDESolvers
Author: Chelsea De Marseilla, Debdal Chowdhury
License: Apache License 2.0
License-File: LICENSE.md
Requires-Dist: matplotlib==3.9.2
Requires-Dist: numpy==2.1.3
Requires-Dist: scipy==1.14.1
Requires-Dist: pandas==2.2.3
Requires-Dist: pytest==8.3.4
Requires-Dist: pytest-cov==6.0.0
Requires-Dist: yfinance==0.2.55
Provides-Extra: package-tools
Requires-Dist: setuptools; extra == "package-tools"
Requires-Dist: wheel; extra == "package-tools"
Requires-Dist: twine; extra == "package-tools"
Dynamic: author
Dynamic: description
Dynamic: description-content-type
Dynamic: home-page
Dynamic: license
Dynamic: provides-extra
Dynamic: requires-dist
Dynamic: summary
